bokku.py
boku-0.0.1.dist-info/METADATA
boku-0.0.1.dist-info/RECORD
boku-0.0.1.dist-info/WHEEL
boku-0.0.1.dist-info/top_level.txt
